Custom/Custom.srcs/sources_1/new/top.v
`timescale 1ns/1ps
module top (
    input clk,
    input rst,
    inout [3:0] rows,
    inout [3:0] cols,
    output reg [3:0] key
);

    // FSM states
    parameter DRIVE_ROWS = 3'b000,
              READ_COLS  = 3'b001,
              DRIVE_COLS = 3'b010,
              READ_ROWS  = 3'b011,
              LATCH_KEY  = 3'b100;

    // Internal regs
    reg [3:0] drive_rows, drive_cols;
    reg [1:0] i, j;
    reg [2:0] state;
    reg [3:0] matrix [0:3][0:3];
    integer x, y;

    // Tri-state bus handling
    assign rows = (state == DRIVE_ROWS || state == READ_COLS) ? drive_rows : 4'bzzzz;
    assign cols = (state == DRIVE_COLS || state == READ_ROWS) ? drive_cols : 4'bzzzz;

    // Matrix init
    initial begin
        for (x = 0; x < 4; x = x + 1)
            for (y = 0; y < 4; y = y + 1)
                matrix[x][y] = x * 4 + y;
    end

    always @(posedge clk or posedge rst) begin
        if (rst) begin
            state <= DRIVE_ROWS;
            i <= 2'bzz;
            j <= 2'bzz;
            key <= 4'bzzzz;
            drive_rows <= 4'b1111;
            drive_cols <= 4'bzzzz;
        end else begin
            case (state)

                DRIVE_ROWS: begin
                    drive_rows <= 4'b1111;
                    drive_cols <= 4'bzzzz;
                    state <= READ_COLS;
                end

                READ_COLS: begin
                    if (cols === 4'bzzzz) begin
                        j <= 2'bzz; state <= READ_COLS;
                    end else begin                 
                        casez (cols)
                            4'b1000: begin j <= 2'b00; state <= DRIVE_COLS; end
                            4'b0100: begin j <= 2'b01; state <= DRIVE_COLS; end
                            4'b0010: begin j <= 2'b10; state <= DRIVE_COLS; end
                            4'b0001: begin j <= 2'b11; state <= DRIVE_COLS; end
                            default: begin j <= 2'bzz; state <= READ_COLS; end         
                        endcase
                    end
                end

                DRIVE_COLS: begin
                    drive_cols <= 4'b1111;
                    drive_rows <= 4'bzzzz;
                    state <= READ_ROWS;
                end

                READ_ROWS: begin
                    if (rows === 4'bzzzz) begin
                        i <= 2'bzz; state <= READ_ROWS;
                    end else begin
                        casez (rows)
                            4'b1000: begin i <= 2'b00; state <= LATCH_KEY; end
                            4'b0100: begin i <= 2'b01; state <= LATCH_KEY; end
                            4'b0010: begin i <= 2'b10; state <= LATCH_KEY; end
                            4'b0001: begin i <= 2'b11; state <= LATCH_KEY; end
                            default: begin i <= 2'bzz; state <= READ_ROWS; end
                        endcase
                    end
                end

                LATCH_KEY: begin
                    if (i !== 2'bzz && j !== 2'bzz)
                        key <= matrix[i][j];
                    state <= DRIVE_ROWS;
                end
            endcase
        end
    end
endmodule

Custom/Custom.srcs/sim_1/new/tb_top.v
`timescale 1ns/1ps
module tb_top;

    reg clk;
    reg rst;
    wire [3:0] rows;
    wire [3:0] cols;
    wire [3:0] key;

    reg [3:0] rows_drive;
    reg [3:0] cols_drive;
    reg [3:0] expected;

    integer i, j;

    // Connect inouts based on FSM drive direction
    assign rows = (uut.state == uut.DRIVE_ROWS || uut.state == uut.READ_COLS) ? uut.drive_rows : rows_drive;
    assign cols = (uut.state == uut.DRIVE_COLS || uut.state == uut.READ_ROWS) ? uut.drive_cols : cols_drive;

    // Instantiate DUT
    top uut (
        .clk(clk),
        .rst(rst),
        .rows(rows),
        .cols(cols),
        .key(key)
    );

    // 66 MHz clock → 15 ns period (7.5 ns half)
    always #7.5 clk = ~clk;

    initial begin
        $dumpfile("tb_top.vcd");
        $dumpvars(0, tb_top);

        clk = 0;
        rst = 1;
        rows_drive = 4'bzzzz;
        cols_drive = 4'bzzzz;
        #45;  // Wait a few cycles
        rst = 0;

        // Loop over all 16 key positions
        for (i = 0; i < 4; i = i + 1) begin
            for (j = 0; j < 4; j = j + 1) begin
                simulate_keypress(i, j);
            end
        end

        #200;
        $display("[%0t] ✅ All keys tested.", $time);
        $finish;
    end

    // Task to simulate one key press and release
    task simulate_keypress(input integer row, input integer col);
        begin
            expected = row * 4 + col;
            $display("\n[%0t] ▶ Testing key at Row=%0d, Col=%0d (Expected=%0d)", $time, row, col, expected);

            // During READ_COLS, drive the selected column
            force cols_drive = (4'b1000 >> col);
            #60; // allow time for FSM to detect col

            // During READ_ROWS, drive the selected row
            force rows_drive = (4'b1000 >> row);
            #60;

            // Release to simulate key release
            release cols_drive;
            release rows_drive;
            #60;

            // Wait for FSM to latch key
            #80;
            if (key === expected)
                $display("[%0t] ✅ Key detected correctly: %0d", $time, key);
            else
                $display("[%0t] ❌ ERROR: Got %0d, expected %0d", $time, key, expected);
        end
    endtask

endmodule

Custom/Custom.sim/sim_1/behav/xsim/tb_top.vcd
$date
   Tue Nov  4 22:09:03 2025
$end

$version
  2025.1.0
  $dumpfile ("tb_top.vcd") 
$end

$timescale
  1ps
$end

$scope module tb_top $end
$var reg 1 ! clk $end
$var reg 1 " rst $end
$var wire 4 # rows [3:0] $end
$var wire 4 $ cols [3:0] $end
$var wire 4 % key [3:0] $end
$var reg 4 & rows_drive [3:0] $end
$var reg 4 ' cols_drive [3:0] $end
$var integer 32 ( i [31:0] $end
$var integer 32 ) j [31:0] $end
$var reg 4 * expected [3:0] $end
$scope module uut $end
$var wire 1 + clk $end
$var wire 1 , rst $end
$var wire 4 # rows [3:0] $end
$var wire 4 $ cols [3:0] $end
$var reg 4 - key [3:0] $end
$var reg 4 . drive_rows [3:0] $end
$var reg 4 / drive_cols [3:0] $end
$var reg 2 0 i [1:0] $end
$var reg 2 1 j [1:0] $end
$var reg 3 2 state [2:0] $end
$var integer 32 3 x [31:0] $end
$var integer 32 4 y [31:0] $end
$upscope $end
$scope task simulate_keypress $end
$var integer 32 5 row [31:0] $end
$var integer 32 6 col [31:0] $end
$upscope $end
$upscope $end
$enddefinitions $end

#0
$dumpvars
0!
1"
bz #
bz $
b0 %
bz &
bz '
bx (
bx )
bx *
0+
1,
b0 -
bz .
bz /
b0 0
b0 1
b0 2
b100 3
b100 4
bx 5
bx 6
$end

#7500
1!
1+

#15000
0!
0+

#22500
1!
1+

#30000
0!
0+

#37500
1!
1+

#45000
0!
0"
b1110 $
b1110 '
b0 (
b0 )
b0 *
0+
0,
b0 5
b0 6

#52500
1!
1+
b0 .
b1 2

#60000
0!
0+

#67500
1!
1+
b10 2

#75000
0!
0+

#82500
1!
bz $
1+
bz .
b11 2

#90000
0!
0+

#97500
1!
b1110 $
1+
b0 /
b100 2

#105000
0!
b1110 #
b1110 &
0+

#112500
1!
1+
b101 2

#120000
0!
0+

#127500
1!
1+
bz /
b110 2

#135000
0!
0+

#142500
1!
bz #
1+
b0 2

#150000
0!
0+

#157500
1!
b1110 #
1+
b0 .
b1 2

#165000
0!
0+

#172500
1!
1+
b10 2

#180000
0!
0+

#187500
1!
bz $
1+
bz .
b11 2

#195000
0!
0+

#202500
1!
b1110 $
1+
b0 /
b100 2

#210000
0!
0+

#217500
1!
1+
b101 2

#225000
0!
0+

#232500
1!
1+
bz /
b110 2

#240000
0!
0+

#245000
b1101 $
b1101 '
b1 )
b1 *
b1 6

#247500
1!
bz #
1+
b0 2

#255000
0!
0+

#262500
1!
b1110 #
1+
b0 .
b1 2

#270000
0!
0+

#277500
1!
1+
b1 1
b10 2

#285000
0!
0+

#292500
1!
bz $
1+
bz .
b11 2

#300000
0!
0+

#307500
1!
b1101 $
1+
b0 /
b100 2

#315000
0!
0+

#322500
1!
1+
b101 2

#330000
0!
0+

#337500
1!
1+
bz /
b110 2

#345000
0!
0+

#352500
1!
bz #
b1 %
1+
b1 -
b0 2

#360000
0!
0+

#367500
1!
b1110 #
1+
b0 .
b1 2

#375000
0!
0+

#382500
1!
1+
b10 2

#390000
0!
0+

#397500
1!
bz $
1+
bz .
b11 2

#405000
0!
0+

#412500
1!
b1101 $
1+
b0 /
b100 2

#420000
0!
0+

#427500
1!
1+
b101 2

#435000
0!
0+

#442500
1!
1+
bz /
b110 2

#445000
b1011 $
b1011 '
b10 )
b10 *
b10 6

#450000
0!
0+

#457500
1!
bz #
1+
b0 2

#465000
0!
0+

#472500
1!
b1110 #
1+
b0 .
b1 2

#480000
0!
0+

#487500
1!
1+
b10 1
b10 2

#495000
0!
0+

#502500
1!
bz $
1+
bz .
b11 2

#510000
0!
0+

#517500
1!
b1011 $
1+
b0 /
b100 2

#525000
0!
0+

#532500
1!
1+
b101 2

#540000
0!
0+

#547500
1!
1+
bz /
b110 2

#555000
0!
0+

#562500
1!
bz #
b10 %
1+
b10 -
b0 2

#570000
0!
0+

#577500
1!
b1110 #
1+
b0 .
b1 2

#585000
0!
0+

#592500
1!
1+
b10 2

#600000
0!
0+

#607500
1!
bz $
1+
bz .
b11 2

#615000
0!
0+

#622500
1!
b1011 $
1+
b0 /
b100 2

#630000
0!
0+

#637500
1!
1+
b101 2

#645000
0!
b111 $
b111 '
b11 )
b11 *
0+
b11 6

#652500
1!
1+
bz /
b110 2

#660000
0!
0+

#667500
1!
bz #
1+
b0 2

#675000
0!
0+

#682500
1!
b1110 #
1+
b0 .
b1 2

#690000
0!
0+

#697500
1!
1+
b11 1
b10 2

#705000
0!
0+

#712500
1!
bz $
1+
bz .
b11 2

#720000
0!
0+

#727500
1!
b111 $
1+
b0 /
b100 2

#735000
0!
0+

#742500
1!
1+
b101 2

#750000
0!
0+

#757500
1!
1+
bz /
b110 2

#765000
0!
0+

#772500
1!
bz #
b11 %
1+
b11 -
b0 2

#780000
0!
0+

#787500
1!
b1110 #
1+
b0 .
b1 2

#795000
0!
0+

#802500
1!
1+
b10 2

#810000
0!
0+

#817500
1!
bz $
1+
bz .
b11 2

#825000
0!
0+

#832500
1!
b111 $
1+
b0 /
b100 2

#840000
0!
0+

#845000
b1110 $
b1110 '
b1 (
b0 )
b100 *
b1 5
b0 6

#847500
1!
1+
b101 2

#855000
0!
0+

#862500
1!
1+
bz /
b110 2

#870000
0!
0+

#877500
1!
bz #
1+
b0 2

#885000
0!
0+

#892500
1!
b1110 #
1+
b0 .
b1 2

#900000
0!
0+

#905000
b1101 #
b1101 &

#907500
1!
1+
b0 1
b10 2

#915000
0!
0+

#922500
1!
bz $
1+
bz .
b11 2

#930000
0!
0+

#937500
1!
b1110 $
1+
b0 /
b100 2

#945000
0!
0+

#952500
1!
1+
b1 0
b101 2

#960000
0!
0+

#967500
1!
1+
bz /
b110 2

#975000
0!
0+

#982500
1!
bz #
b100 %
1+
b100 -
b0 2

#990000
0!
0+

#997500
1!
b1101 #
1+
b0 .
b1 2

#1005000
0!
0+

#1012500
1!
1+
b10 2

#1020000
0!
0+

#1027500
1!
bz $
1+
bz .
b11 2

#1035000
0!
0+

#1042500
1!
b1110 $
1+
b0 /
b100 2

#1045000
b1101 $
b1101 '
b1 )
b101 *
b1 6

#1050000
0!
0+

#1057500
1!
1+
b101 2

#1065000
0!
0+

#1072500
1!
1+
bz /
b110 2

#1080000
0!
0+

#1087500
1!
bz #
1+
b0 2

#1095000
0!
0+

#1102500
1!
b1101 #
1+
b0 .
b1 2

#1110000
0!
0+

#1117500
1!
1+
b1 1
b10 2

#1125000
0!
0+

#1132500
1!
bz $
1+
bz .
b11 2

#1140000
0!
0+

#1147500
1!
b1101 $
1+
b0 /
b100 2

#1155000
0!
0+

#1162500
1!
1+
b101 2

#1170000
0!
0+

#1177500
1!
1+
bz /
b110 2

#1185000
0!
0+

#1192500
1!
bz #
b101 %
1+
b101 -
b0 2

#1200000
0!
0+

#1207500
1!
b1101 #
1+
b0 .
b1 2

#1215000
0!
0+

#1222500
1!
1+
b10 2

#1230000
0!
0+

#1237500
1!
bz $
1+
bz .
b11 2

#1245000
0!
b1011 '
b10 )
b110 *
0+
b10 6

#1252500
1!
b1011 $
1+
b0 /
b100 2

#1260000
0!
0+

#1267500
1!
1+
b101 2

#1275000
0!
0+

#1282500
1!
1+
bz /
b110 2

#1290000
0!
0+

#1297500
1!
bz #
1+
b0 2

#1305000
0!
0+

#1312500
1!
b1101 #
1+
b0 .
b1 2

#1320000
0!
0+

#1327500
1!
1+
b10 1
b10 2

#1335000
0!
0+

#1342500
1!
bz $
1+
bz .
b11 2

#1350000
0!
0+

#1357500
1!
b1011 $
1+
b0 /
b100 2

#1365000
0!
0+

#1372500
1!
1+
b101 2

#1380000
0!
0+

#1387500
1!
1+
bz /
b110 2

#1395000
0!
0+

#1402500
1!
bz #
b110 %
1+
b110 -
b0 2

#1410000
0!
0+

#1417500
1!
b1101 #
1+
b0 .
b1 2

#1425000
0!
0+

#1432500
1!
1+
b10 2

#1440000
0!
0+

#1445000
b111 $
b111 '
b11 )
b111 *
b11 6

#1447500
1!
bz $
1+
bz .
b11 2

#1455000
0!
0+

#1462500
1!
b111 $
1+
b0 /
b100 2

#1470000
0!
0+

#1477500
1!
1+
b101 2

#1485000
0!
0+

#1492500
1!
1+
bz /
b110 2

#1500000
0!
0+

#1507500
1!
bz #
1+
b0 2

#1515000
0!
0+

#1522500
1!
b1101 #
1+
b0 .
b1 2

#1530000
0!
0+

#1537500
1!
1+
b11 1
b10 2

#1545000
0!
0+

#1552500
1!
bz $
1+
bz .
b11 2

#1560000
0!
0+

#1567500
1!
b111 $
1+
b0 /
b100 2

#1575000
0!
0+

#1582500
1!
1+
b101 2

#1590000
0!
0+

#1597500
1!
1+
bz /
b110 2

#1605000
0!
0+

#1612500
1!
bz #
b111 %
1+
b111 -
b0 2

#1620000
0!
0+

#1627500
1!
b1101 #
1+
b0 .
b1 2

#1635000
0!
0+

#1642500
1!
1+
b10 2

#1645000
b1110 $
b1110 '
b10 (
b0 )
b1000 *
b10 5
b0 6

#1650000
0!
0+

#1657500
1!
bz $
1+
bz .
b11 2

#1665000
0!
0+

#1672500
1!
b1110 $
1+
b0 /
b100 2

#1680000
0!
0+

#1687500
1!
1+
b101 2

#1695000
0!
0+

#1702500
1!
1+
bz /
b110 2

#1705000
b1011 #
b1011 &

#1710000
0!
0+

#1717500
1!
bz #
1+
b0 2

#1725000
0!
0+

#1732500
1!
b1011 #
1+
b0 .
b1 2

#1740000
0!
0+

#1747500
1!
1+
b0 1
b10 2

#1755000
0!
0+

#1762500
1!
bz $
1+
bz .
b11 2

#1770000
0!
0+

#1777500
1!
b1110 $
1+
b0 /
b100 2

#1785000
0!
0+

#1792500
1!
1+
b10 0
b101 2

#1800000
0!
0+

#1807500
1!
1+
bz /
b110 2

#1815000
0!
0+

#1822500
1!
bz #
b1000 %
1+
b1000 -
b0 2

#1830000
0!
0+

#1837500
1!
b1011 #
1+
b0 .
b1 2

#1845000
0!
b1101 $
b1101 '
b1 )
b1001 *
0+
b1 6

#1852500
1!
1+
b1 1
b10 2

#1860000
0!
0+

#1867500
1!
bz $
1+
bz .
b11 2

#1875000
0!
0+

#1882500
1!
b1101 $
1+
b0 /
b100 2

#1890000
0!
0+

#1897500
1!
1+
b101 2

#1905000
0!
0+

#1912500
1!
1+
bz /
b110 2

#1920000
0!
0+

#1927500
1!
bz #
b1001 %
1+
b1001 -
b0 2

#1935000
0!
0+

#1942500
1!
b1011 #
1+
b0 .
b1 2

#1950000
0!
0+

#1957500
1!
1+
b10 2

#1965000
0!
0+

#1972500
1!
bz $
1+
bz .
b11 2

#1980000
0!
0+

#1987500
1!
b1101 $
1+
b0 /
b100 2

#1995000
0!
0+

#2002500
1!
1+
b101 2

#2010000
0!
0+

#2017500
1!
1+
bz /
b110 2

#2025000
0!
0+

#2032500
1!
bz #
1+
b0 2

#2040000
0!
0+

#2045000
b1011 $
b1011 '
b10 )
b1010 *
b10 6

#2047500
1!
b1011 #
1+
b0 .
b1 2

#2055000
0!
0+

#2062500
1!
1+
b10 1
b10 2

#2070000
0!
0+

#2077500
1!
bz $
1+
bz .
b11 2

#2085000
0!
0+

#2092500
1!
b1011 $
1+
b0 /
b100 2

#2100000
0!
0+

#2107500
1!
1+
b101 2

#2115000
0!
0+

#2122500
1!
1+
bz /
b110 2

#2130000
0!
0+

#2137500
1!
bz #
b1010 %
1+
b1010 -
b0 2

#2145000
0!
0+

#2152500
1!
b1011 #
1+
b0 .
b1 2

#2160000
0!
0+

#2167500
1!
1+
b10 2

#2175000
0!
0+

#2182500
1!
bz $
1+
bz .
b11 2

#2190000
0!
0+

#2197500
1!
b1011 $
1+
b0 /
b100 2

#2205000
0!
0+

#2212500
1!
1+
b101 2

#2220000
0!
0+

#2227500
1!
1+
bz /
b110 2

#2235000
0!
0+

#2242500
1!
bz #
1+
b0 2

#2245000
b111 $
b111 '
b11 )
b1011 *
b11 6

#2250000
0!
0+

#2257500
1!
b1011 #
1+
b0 .
b1 2

#2265000
0!
0+

#2272500
1!
1+
b11 1
b10 2

#2280000
0!
0+

#2287500
1!
bz $
1+
bz .
b11 2

#2295000
0!
0+

#2302500
1!
b111 $
1+
b0 /
b100 2

#2310000
0!
0+

#2317500
1!
1+
b101 2

#2325000
0!
0+

#2332500
1!
1+
bz /
b110 2

#2340000
0!
0+

#2347500
1!
bz #
b1011 %
1+
b1011 -
b0 2

#2355000
0!
0+

#2362500
1!
b1011 #
1+
b0 .
b1 2

#2370000
0!
0+

#2377500
1!
1+
b10 2

#2385000
0!
0+

#2392500
1!
bz $
1+
bz .
b11 2

#2400000
0!
0+

#2407500
1!
b111 $
1+
b0 /
b100 2

#2415000
0!
0+

#2422500
1!
1+
b101 2

#2430000
0!
0+

#2437500
1!
1+
bz /
b110 2

#2445000
0!
b1110 $
b1110 '
b11 (
b0 )
b1100 *
0+
b11 5
b0 6

#2452500
1!
bz #
1+
b0 2

#2460000
0!
0+

#2467500
1!
b1011 #
1+
b0 .
b1 2

#2475000
0!
0+

#2482500
1!
1+
b0 1
b10 2

#2490000
0!
0+

#2497500
1!
bz $
1+
bz .
b11 2

#2505000
0!
b111 #
b111 &
0+

#2512500
1!
b1110 $
1+
b0 /
b100 2

#2520000
0!
0+

#2527500
1!
1+
b11 0
b101 2

#2535000
0!
0+

#2542500
1!
1+
bz /
b110 2

#2550000
0!
0+

#2557500
1!
bz #
b1100 %
1+
b1100 -
b0 2

#2565000
0!
0+

#2572500
1!
b111 #
1+
b0 .
b1 2

#2580000
0!
0+

#2587500
1!
1+
b10 2

#2595000
0!
0+

#2602500
1!
bz $
1+
bz .
b11 2

#2610000
0!
0+

#2617500
1!
b1110 $
1+
b0 /
b100 2

#2625000
0!
0+

#2632500
1!
1+
b101 2

#2640000
0!
0+

#2645000
b1101 $
b1101 '
b1 )
b1101 *
b1 6

#2647500
1!
1+
bz /
b110 2

#2655000
0!
0+

#2662500
1!
bz #
1+
b0 2

#2670000
0!
0+

#2677500
1!
b111 #
1+
b0 .
b1 2

#2685000
0!
0+

#2692500
1!
1+
b1 1
b10 2

#2700000
0!
0+

#2707500
1!
bz $
1+
bz .
b11 2

#2715000
0!
0+

#2722500
1!
b1101 $
1+
b0 /
b100 2

#2730000
0!
0+

#2737500
1!
1+
b101 2

#2745000
0!
0+

#2752500
1!
1+
bz /
b110 2

#2760000
0!
0+

#2767500
1!
bz #
b1101 %
1+
b1101 -
b0 2

#2775000
0!
0+

#2782500
1!
b111 #
1+
b0 .
b1 2

#2790000
0!
0+

#2797500
1!
1+
b10 2

#2805000
0!
0+

#2812500
1!
bz $
1+
bz .
b11 2

#2820000
0!
0+

#2827500
1!
b1101 $
1+
b0 /
b100 2

#2835000
0!
0+

#2842500
1!
1+
b101 2

#2845000
b1011 $
b1011 '
b10 )
b1110 *
b10 6

#2850000
0!
0+

#2857500
1!
1+
bz /
b110 2

#2865000
0!
0+

#2872500
1!
bz #
1+
b0 2

#2880000
0!
0+

#2887500
1!
b111 #
1+
b0 .
b1 2

#2895000
0!
0+

#2902500
1!
1+
b10 1
b10 2

#2910000
0!
0+

#2917500
1!
bz $
1+
bz .
b11 2

#2925000
0!
0+

#2932500
1!
b1011 $
1+
b0 /
b100 2

#2940000
0!
0+

#2947500
1!
1+
b101 2

#2955000
0!
0+

#2962500
1!
1+
bz /
b110 2

#2970000
0!
0+

#2977500
1!
bz #
b1110 %
1+
b1110 -
b0 2

#2985000
0!
0+

#2992500
1!
b111 #
1+
b0 .
b1 2

#3000000
0!
0+

#3007500
1!
1+
b10 2

#3015000
0!
0+

#3022500
1!
bz $
1+
bz .
b11 2

#3030000
0!
0+

#3037500
1!
b1011 $
1+
b0 /
b100 2

#3045000
0!
b111 $
b111 '
b11 )
b1111 *
0+
b11 6

#3052500
1!
1+
b101 2

#3060000
0!
0+

#3067500
1!
1+
bz /
b110 2

#3075000
0!
0+

#3082500
1!
bz #
1+
b0 2

#3090000
0!
0+

#3097500
1!
b111 #
1+
b0 .
b1 2

#3105000
0!
0+

#3112500
1!
1+
b11 1
b10 2

#3120000
0!
0+

#3127500
1!
bz $
1+
bz .
b11 2

#3135000
0!
0+

#3142500
1!
b111 $
1+
b0 /
b100 2

#3150000
0!
0+

#3157500
1!
1+
b101 2

#3165000
0!
0+

#3172500
1!
1+
bz /
b110 2

#3180000
0!
0+

#3187500
1!
bz #
b1111 %
1+
b1111 -
b0 2

#3195000
0!
0+

#3202500
1!
b111 #
1+
b0 .
b1 2

#3210000
0!
0+

#3217500
1!
1+
b10 2

#3225000
0!
0+

#3232500
1!
bz $
1+
bz .
b11 2

#3240000
0!
0+

#3245000
b100 (
b100 )

#3247500
1!
b111 $
1+
b0 /
b100 2

#3255000
0!
0+

#3262500
1!
1+
b101 2

#3270000
0!
0+

#3277500
1!
1+
bz /
b110 2

#3285000
0!
0+

#3292500
1!
bz #
1+
b0 2

#3300000
0!
0+

#3307500
1!
b111 #
1+
b0 .
b1 2

#3315000
0!
0+

#3322500
1!
1+
b10 2

#3330000
0!
0+

#3337500
1!
bz $
1+
bz .
b11 2

#3345000
0!
0+

#3352500
1!
b111 $
1+
b0 /
b100 2

#3360000
0!
0+

#3367500
1!
1+
b101 2

#3375000
0!
0+

#3382500
1!
1+
bz /
b110 2

#3390000
0!
0+

#3397500
1!
bz #
1+
b0 2

#3405000
0!
0+

#3412500
1!
b111 #
1+
b0 .
b1 2

#3420000
0!
0+

#3427500
1!
1+
b10 2

#3435000
0!
0+

#3442500
1!
bz $
1+
bz .
b11 2
