Default/Default.srcs/sources_1/new/top.v
module top (
  input            clk,
  input            reset,       /* additional input */
  input      [3:0] col,
  output reg [3:0] row,
  output reg [7:0] keycode,
  output reg       keyValid     /* additional output */
);

  always @(posedge clk) begin
    if (reset) begin
      /* Reset all register variables.
       * Not strictly necessary for synthesis,
       * but the simulator will require it.
       */
      row <= 4'b1000;
      keycode <= 8'b0;
      keyValid <= 0;
    end else begin
      /* If any column is active in the current row,
       * output the row and column pattern as a keyCode,
       * and assert keyValid. Pause the scanning as long
       * as the key is held down.
       */
      if (col != 4'b0000) begin
        keycode <= {col, row};
        keyValid <= 1;
      end else begin
        keyValid <= 0;
        /* Scan the matrix, one row per clock period
         */
        case (row)
          4'b1000: row <= 4'b0100;
          4'b0100: row <= 4'b0010;
          4'b0010: row <= 4'b0001;
          4'b0001: row <= 4'b1000;
          default: row <= 4'b1000;
        endcase
      end
    end
  end

endmodule

Default/Default.srcs/sim_1/new/tb.v
`timescale 1ns / 1ps

module tb;

  // Parameters
  localparam CLK_PERIOD = 10; // 10 ns clock period (100 MHz)

  // Testbench Signals
  reg         clk;
  reg         reset;
  reg   [3:0] col;
  wire  [3:0] row;
  wire  [7:0] keycode;
  wire        keyValid;

  // Instantiate the Device Under Test (DUT)
  top dut (
    .clk(clk),
    .reset(reset),
    .col(col),
    .row(row),
    .keycode(keycode),
    .keyValid(keyValid)
  );

  // Clock Generation
  initial begin
    clk = 0;
    forever #(CLK_PERIOD / 2) clk = ~clk;
  end

  // Test Sequence
  initial begin
    $display("Time=%0t [TB] Starting simulation...", $time);

    // Dump waves for debugging
    $dumpfile("tb.vcd");
    $dumpvars(0, tb);

    // 1. Initialize and Reset
    reset = 1;
    col   = 4'b0000; // No key pressed
    $display("Time=%0t [TB] Asserting reset.", $time);
    
    @(posedge clk);
    @(posedge clk); // Hold reset for 2 cycles
    
    reset = 0;
    $display("Time=%0t [TB] De-asserting reset. DUT should start scanning.", $time);
    
    @(posedge clk);
    if (row !== 4'b1000) $display("Time=%0t [TB] FAIL: Row not 1000 after reset.", $time);

    // 2. Test Case: No Key Press (let it scan)
    $display("Time=%0t [TB] TESTCASE 1: No key press. Checking scan cycle...", $time);
    
    @(posedge clk); // Scan logic runs
    if (row !== 4'b0100) $display("Time=%0t [TB] FAIL: Row did not scan to 0100.", $time);
    
    @(posedge clk); // Scan logic runs
    if (row !== 4'b0010) $display("Time=%0t [TB] FAIL: Row did not scan to 0010.", $time);
    
    @(posedge clk); // Scan logic runs
    if (row !== 4'b0001) $display("Time=%0t [TB] FAIL: Row did not scan to 0001.", $time);
    
    @(posedge clk); // Scan logic runs (wraps around)
    if (row !== 4'b1000) $display("Time=%0t [TB] FAIL: Row did not wrap to 1000.", $time);
    
    $display("Time=%0t [TB] TESTCASE 1: Scan OK.", $time);

    // 3. Test Case: Press Key (Row 2, Col 1)
    $display("Time=%0t [TB] TESTCASE 2: Pressing key (R2, C1)...", $time);
    
    @(posedge clk); // row=1000, next should be 0100
    // Current row is 4'b0100 (Row 2). Let's press Col 1.
    col = 4'b0001; 
    
    @(posedge clk); // DUT should detect the key press
    $display("Time=%0t [TB] Key pressed. keyValid=%b, keycode=%h, row=%b", $time, keyValid, keycode, row);
    if (keyValid !== 1) $display("Time=%0t [TB] FAIL: keyValid is not 1.", $time);
    if (keycode !== 8'h14) $display("Time=%0t [TB] FAIL: keycode is not 8'h14 ({0001, 0100}).", $time);
    if (row !== 4'b0100) $display("Time=%0t [TB] FAIL: Row did not pause scanning.", $time);

    // 4. Test Case: Hold Key
    $display("Time=%0t [TB] TESTCASE 3: Holding key for 3 cycles...", $time);
    @(posedge clk);
    @(posedge clk);
    @(posedge clk);
    if (keyValid !== 1) $display("Time=%0t [TB] FAIL: keyValid dropped while key held.", $time);
    if (row !== 4'b0100) $display("Time=%0t [TB] FAIL: Row did not stay paused.", $time);
    $display("Time=%0t [TB] TESTCASE 3: Key hold OK.", $time);

    // 5. Test Case: Release Key
    $display("Time=%0t [TB] TESTCASE 4: Releasing key...", $time);
    col = 4'b0000;
    
    @(posedge clk); // DUT should detect release and resume scan
    $display("Time=%0t [TB] Key released. keyValid=%b, row=%b", $time, keyValid, row);
    if (keyValid !== 0) $display("Time=%0t [TB] FAIL: keyValid did not go to 0.", $time);
    if (row !== 4'b0010) $display("Time=%0t [TB] FAIL: Row did not resume scan (expected 0010).", $time);
        
    @(posedge clk); // Continue scan
    if (row !== 4'b0001) $display("Time=%0t [TB] FAIL: Scan did not continue to 0001.", $time);
    $display("Time=%0t [TB] TESTCASE 4: Key release and resume OK.", $time);
    
    // 6. Test Case: Press Key (Row 4, Col 3)
    $display("Time=%0t [TB] TESTCASE 5: Pressing key (R4, C3)...", $time);
    // We are currently at row 4'b0001 (Row 4). Press Col 3.
    col = 4'b0100;
    
    @(posedge clk); // DUT should detect key press
    $display("Time=%0t [TB] Key pressed. keyValid=%b, keycode=%h, row=%b", $time, keyValid, keycode, row);
    if (keyValid !== 1) $display("Time=%0t [TB] FAIL: keyValid is not 1.", $time);
    if (keycode !== 8'h41) $display("Time=%0t [TB] FAIL: keycode is not 8'h41 ({0100, 0001}).", $time);
    if (row !== 4'b0001) $display("Time=%0t [TB] FAIL: Row did not pause scanning.", $time);

    // 7. Release key and finish
    col = 4'b0000;
    @(posedge clk);
    $display("Time=%0t [TB] Key released. keyValid=%b, row=%b", $time, keyValid, row);
    if (row !== 4'b1000) $display("Time=%0t [TB] FAIL: Row did not resume scan (expected 1000).", $time);
    
    #(CLK_PERIOD * 10); // Wait a few more cycles
    $display("Time=%0t [TB] Simulation finished.", $time);
    $stop;
  end

endmodule

Default/Default.sim/sim_1/behav/tb.vcd
$date
   Wed Nov 05 16:38:03 2025
$end
$version
  2016.4
$end
$timescale
  1ps
$end
$scope module tb $end
$var reg 1 ! clk $end
$var reg 1 " reset $end
$var reg 4 # col [3:0] $end
$var wire 4 $ row [3:0] $end
$var wire 8 % keycode [7:0] $end
$var wire 1 & keyValid $end
$var parameter 32 ' CLK_PERIOD [31:0] $end
$scope module dut $end
$var wire 1 ( clk $end
$var wire 1 ) reset $end
$var wire 4 * col [3:0] $end
$var reg 4 + row [3:0] $end
$var reg 8 , keycode [7:0] $end
$var reg 1 - keyValid $end
$upscope $end
$upscope $end
$enddefinitions $end
#0
$dumpvars
0!
1"
b0 #
bx $
bx %
x&
b1010 '
0(
1)
b0 *
bx +
bx ,
x-
$end
#5000
1!
b1000 $
b0 %
0&
1(
b1000 +
b0 ,
0-
#10000
0!
0(
#15000
1!
0"
b100 $
1(
0)
b100 +
0-
#20000
0!
0(
#25000
1!
b10 $
1(
b10 +
0-
#30000
0!
0(
#35000
1!
b1 $
1(
b1 +
0-
#40000
0!
0(
#45000
1!
b1000 $
1(
b1000 +
0-
#50000
0!
0(
#55000
1!
b100 $
1(
b100 +
0-
#60000
0!
0(
#65000
1!
b10 $
1(
b10 +
0-
#70000
0!
0(
#75000
1!
b1 #
b10010 %
1&
1(
b1 *
b10010 ,
1-
#80000
0!
0(
#85000
1!
1(
b10010 ,
1-
#90000
0!
0(
#95000
1!
1(
b10010 ,
1-
#100000
0!
0(
#105000
1!
1(
b10010 ,
1-
#110000
0!
0(
#115000
1!
b0 #
b1 $
0&
1(
b0 *
b1 +
0-
#120000
0!
0(
#125000
1!
b1000 $
1(
b1000 +
0-
#130000
0!
0(
#135000
1!
b100 #
b1001000 %
1&
1(
b100 *
b1001000 ,
1-
#140000
0!
0(
#145000
1!
b0 #
b100 $
0&
1(
b0 *
b100 +
0-
#150000
0!
0(
#155000
1!
b10 $
1(
b10 +
0-
#160000
0!
0(
#165000
1!
b1 $
1(
b1 +
0-
#170000
0!
0(
#175000
1!
b1000 $
1(
b1000 +
0-
#180000
0!
0(
#185000
1!
b100 $
1(
b100 +
0-
#190000
0!
0(
#195000
1!
b10 $
1(
b10 +
0-
#200000
0!
0(
#205000
1!
b1 $
1(
b1 +
0-
#210000
0!
0(
#215000
1!
b1000 $
1(
b1000 +
0-
#220000
0!
0(
#225000
1!
b100 $
1(
b100 +
0-
#230000
0!
0(
#235000
1!
b10 $
1(
b10 +
0-
#240000
0!
0(
#245000
1!
b1 $
1(
b1 +
0-
